{
  "$schema": "https://mintlify.com/docs.json",
  "theme": "mint",
  "name": "MCP Blacksmith Docs",
  "colors": {
    "primary": "#ff5722",
    "light": "#ff7043",
    "dark": "#e64a19"
  },
  "background": {
    "color": {
      "dark": "#1a1a1a",
      "light": "#faf7f2"
    }
  },
  "appearance": {
    "default": "dark",
    "strict": true
  },
  "favicon": "/favicon.png",
  "logo": {
    "light": "/logo/light.svg",
    "dark": "/logo/dark.svg",
    "href": "https://mcpblacksmith.com"
  },
  "navigation": {
    "tabs": [
      {
        "tab": "Documentation",
        "groups": [
          {
            "group": "Getting Started",
            "pages": [
              "index",
              "how-it-works",
              "quickstart"
            ]
          },
          {
            "group": "Generation",
            "pages": [
              "generation/spec-upload",
              "generation/free-generation",
              "generation/enhancement-passes",
              "generation/validation",
              "generation/linting"
            ]
          },
          {
            "group": "Your Generated Server",
            "pages": [
              "server/structure",
              "server/authentication",
              "server/security",
              "server/customizing"
            ]
          },
          {
            "group": "Deployment",
            "pages": [
              "deployment/local",
              "deployment/self-hosting",
              "deployment/connecting-agents"
            ]
          },
          {
            "group": "Reference",
            "pages": [
              "reference/supported-features",
              "reference/troubleshooting",
              "reference/faq"
            ]
          }
        ]
      }
    ],
    "global": {
      "anchors": []
    }
  },
  "navbar": {
    "links": [
      {
        "label": "Contact",
        "href": "https://mcpblacksmith.com/contact"
      }
    ],
    "primary": {
      "type": "button",
      "label": "Start Forging",
      "href": "https://mcpblacksmith.com/dashboard"
    }
  },
  "contextual": {
    "options": []
  },
  "footer": {
    "socials": {
      "linkedin": "https://www.linkedin.com/company/mcp-blacksmith/"
    }
  },
  "seo": {
    "metatags": {
      "canonical": "https://docs.mcpblacksmith.com"
    }
  }
}
